robotpy/__init__.py
robotpy/__main__.py
robotpy/logconfig.py
robotpy/main.py
robotpy/py.typed
robotpy_cli-2024.0.0b2.dist-info/LICENSE
robotpy_cli-2024.0.0b2.dist-info/METADATA
robotpy_cli-2024.0.0b2.dist-info/WHEEL
robotpy_cli-2024.0.0b2.dist-info/entry_points.txt
robotpy_cli-2024.0.0b2.dist-info/top_level.txt
robotpy_cli-2024.0.0b2.dist-info/RECORD
