Metadata-Version: 2.1
Name: robotpy-cli
Version: 2024.0.0b2
Author-email: Dustin Spicuzza <robotpy@googlegroups.com>
License: Copyright © Dustin Spicuzza and contributors
Project-URL: repository, https://github.com/robotpy/robotpy-cli
Requires-Python: >=3.8
License-File: LICENSE
